pydelling/__init__.py
pydelling/config/__init__.py
pydelling/config/conda_env.yaml
pydelling/config/global_config.yaml
pydelling/config/local_config.yaml
pydelling/config/logger_config.yaml
pydelling/estimators/BaseEstimator.py
pydelling/estimators/PolygonZoneEstimator.py
pydelling/estimators/__init__.py
pydelling/interpolation/BaseInterpolator.py
pydelling/interpolation/KdeEstimator.py
pydelling/interpolation/SparseDataInterpolator.py
pydelling/interpolation/__init__.py
pydelling/managers/BaseManager.py
pydelling/managers/BaseStudy.py
pydelling/managers/PflotranManager.py
pydelling/managers/PflotranPostprocessing.py
pydelling/managers/PflotranStudy.py
pydelling/managers/__init__.py
pydelling/managers/callbacks/BaseCallback.py
pydelling/managers/callbacks/PflotranRestartCallback.py
pydelling/managers/callbacks/PflotranSaveResultsCallback.py
pydelling/managers/callbacks/__init__.py
pydelling/managers/ssh/BaseSsh.py
pydelling/managers/ssh/JurecaSsh.py
pydelling/managers/ssh/LumiSsh.py
pydelling/managers/ssh/__init__.py
pydelling/managers/ssh/steps/BaseStep.py
pydelling/managers/ssh/steps/CopyStep.py
pydelling/managers/ssh/steps/__init__.py
pydelling/managers/status/BaseStatus.py
pydelling/managers/status/PflotranStatus.py
pydelling/managers/status/__init__.py
pydelling/paraview_processor/ParaviewProcessor.py
pydelling/paraview_processor/__init__.py
pydelling/paraview_processor/filters/AppendArcLengthFilter.py
pydelling/paraview_processor/filters/BaseFilter.py
pydelling/paraview_processor/filters/CalculatorFilter.py
pydelling/paraview_processor/filters/CellDataToPointDataFilter.py
pydelling/paraview_processor/filters/ClipFilter.py
pydelling/paraview_processor/filters/CsvReaderFilter.py
pydelling/paraview_processor/filters/IntegrateVariablesFilter.py
pydelling/paraview_processor/filters/PlotOverLineFilter.py
pydelling/paraview_processor/filters/SaveDataFilter.py
pydelling/paraview_processor/filters/StreamTracerWithCustomSourceFilter.py
pydelling-1.13.dist-info/LICENSE.txt
pydelling-1.13.dist-info/METADATA
pydelling-1.13.dist-info/WHEEL
pydelling-1.13.dist-info/RECORD
