Metadata-Version: 2.1
Name: pydelling
Version: 1.13
Summary: Package providing a variety of utility methods for mathematical modelling
License: MIT
Author: Aitor
Author-email: aitirga@gmail.com
Requires-Python: >=3.8,<3.11
Classifier: License :: OSI Approved :: MIT License
Classifier: Programming Language :: Python :: 3
Classifier: Programming Language :: Python :: 3.8
Classifier: Programming Language :: Python :: 3.9
Classifier: Programming Language :: Python :: 3.10
Requires-Dist: alive-progress
Requires-Dist: charset-normalizer (>=3.1.0,<4.0.0)
Requires-Dist: dill
Requires-Dist: docker
Requires-Dist: h5py
Requires-Dist: matplotlib
Requires-Dist: meshio
Requires-Dist: mkdocs
Requires-Dist: mkdocs-material
Requires-Dist: mkdocstrings
Requires-Dist: mpmath
Requires-Dist: natsort
Requires-Dist: numpy
Requires-Dist: numpy-stl
Requires-Dist: ofpp
Requires-Dist: openpyxl
Requires-Dist: pandas
Requires-Dist: paramiko
Requires-Dist: plotly
Requires-Dist: python-box
Requires-Dist: pyyaml
Requires-Dist: rich
Requires-Dist: rtree
Requires-Dist: scikit-image (>=0.21.0,<0.22.0)
Requires-Dist: scikit-learn
Requires-Dist: scipy
Requires-Dist: seaborn
Requires-Dist: setuptools
Requires-Dist: shapely
Requires-Dist: sklearn
Requires-Dist: streamlit
Requires-Dist: tabulate
Requires-Dist: tqdm
Requires-Dist: trimesh
Requires-Dist: vtk
Requires-Dist: xlrd
